.bumpversion.cfg
.cookiecutterrc
.coveragerc
.editorconfig
.gitignore
.travis.yml
AUTHORS.rst
CHANGELOG.rst
CONTRIBUTING.rst
LICENSE
MANIFEST.in
README.rst
appveyor.yml
setup.cfg
setup.py
tox.ini
ci/appveyor-bootstrap.py
ci/appveyor-download.py
ci/appveyor-with-compiler.cmd
ci/bootstrap.py
ci/templates/.travis.yml
ci/templates/appveyor.yml
ci/templates/.travis.yml
ci/templates/appveyor.yml
docs/authors.rst
docs/changelog.rst
docs/conf.py
docs/contributing.rst
docs/index.rst
docs/installation.rst
docs/readme.rst
docs/requirements.txt
docs/spelling_wordlist.txt
docs/usage.rst
docs/reference/index.rst
docs/reference/mfs.rst
docs/reference/index.rst
docs/reference/mfs.rst
src/mfs/__init__.py
src/mfs/__main__.py
src/mfs/cli.py
src/mfs/scrape.py
src/mfs/__init__.py
src/mfs/__main__.py
src/mfs/cli.py
src/mfs/scrape.py
src/mfs.egg-info/PKG-INFO
src/mfs.egg-info/SOURCES.txt
src/mfs.egg-info/dependency_links.txt
src/mfs.egg-info/entry_points.txt
src/mfs.egg-info/not-zip-safe
src/mfs.egg-info/requires.txt
src/mfs.egg-info/top_level.txt
tests/test_mfs.py
tests/test_scrape.py
tests/data/keep4u.ru.html
tests/data/keep4u.ru.jpg
tests/data/overview.html
tests/data/postimage.org.html
tests/data/postimg.org.jpg
tests/data/radikal.ru.html
tests/data/radikal.ru.jpg
tests/data/vfl.ru.html
tests/data/vfl.ru.jpg
tests/data/fastpic.ru.html
tests/data/fastpic.ru.jpg
tests/data/keep4u.ru.html
tests/data/keep4u.ru.jpg
tests/data/overview.html
tests/data/postimage.org.html
tests/data/postimg.org.jpg
tests/data/radikal.ru.html
tests/data/radikal.ru.jpg
tests/data/vfl.ru.html
tests/data/vfl.ru.jpg