Metadata-Version: 1.1
Name: mfs
Version: 0.1.1
Summary: mfs is a set of utilities to ease image download from some Russian modelling forums
Home-page: https://github.com/miroag/mfs
Author: Alexandre Ovtchinnikov
Author-email: miroag64@gmail.com
License: MIT license
Platform: UNKNOWN
Classifier: Development Status :: 5 - Production/Stable
Classifier: Intended Audience :: Developers
Classifier: License :: OSI Approved :: MIT License
Classifier: Operating System :: Unix
Classifier: Operating System :: POSIX
Classifier: Operating System :: Microsoft :: Windows
Classifier: Programming Language :: Python
Classifier: Programming Language :: Python :: 3.5
Classifier: Programming Language :: Python :: 3.6
Classifier: Programming Language :: Python :: Implementation :: CPython
Classifier: Programming Language :: Python :: Implementation :: PyPy
Classifier: Topic :: Utilities
